{"results":[{"id":"alexandria_rom_prov","text":"Alexandria","level":4,"short":0,"flag_type":"m","flag_code":"","section":0,"period":0},{"id":"galatia_province","text":"Galatia","level":3,"short":0,"flag_type":"s","flag_code":"roman-provinces","section":1,"period":0},{"id":"ancyra_galatia_rom_prov","text":"Ancyra","level":4,"short":0,"flag_type":"m","flag_code":"","section":0,"period":0},{"id":"antioch_galatia_rom_prov","text":"Antioch of Pisidia","level":4,"short":0,"flag_type":"m","flag_code":"","section":0,"period":0},{"id":"apollonia_mordiaeum_rom_prov","text":"Apollonia Mordiaeum","level":4,"short":0,"flag_type":"m","flag_code":"","section":0,"period":0},{"id":"cremna_rom_prov","text":"Cremna","level":4,"short":0,"flag_type":"m","flag_code":"","section":0,"period":0},{"id":"galatia_kingdom_rom_prov","text":"Galatia, Kingdom of","level":4,"short":0,"flag_type":"m","flag_code":"","section":0,"period":0},{"id":"koinon_galatia_rom_prov","text":"Galatia, Koinon of","level":4,"short":0,"flag_type":"m","flag_code":"","section":0,"period":0},{"id":"gangra_germanicopolis_rom_prov","text":"Gangra-Germanicopolis","level":4,"short":0,"flag_type":"m","flag_code":"","section":0,"period":0},{"id":"germa_rom_prov","text":"Germa","level":4,"short":0,"flag_type":"m","flag_code":"","section":0,"period":0},{"id":"iconium_rom_prov","text":"Iconium","level":4,"short":0,"flag_type":"m","flag_code":"","section":0,"period":0},{"id":"ionopolis_abonoteichos_galatia_rom_prov","text":"Ionopolis Abonoteichos","level":4,"short":1,"flag_type":"m","flag_code":"","section":0,"period":0},{"id":"lystra_rom_prov","text":"Lystra","level":4,"short":0,"flag_type":"m","flag_code":"","section":0,"period":0},{"id":"neoclaudiopolis_rom_prov","text":"Neoclaudiopolis","level":4,"short":0,"flag_type":"m","flag_code":"","section":0,"period":0},{"id":"paphlagonia_kingdom_rom_prov","text":"Paphlagonia, Kingdom of","level":4,"short":0,"flag_type":"m","flag_code":"","section":0,"period":0},{"id":"pappa_tiberia_rom_prov","text":"Pappa Tiberia","level":4,"short":0,"flag_type":"m","flag_code":"","section":0,"period":0},{"id":"pessinus_rom_prov","text":"Pessinus","level":4,"short":0,"flag_type":"m","flag_code":"","section":0,"period":0},{"id":"pompeiopolis_galatia_rom_prov","text":"Pompeiopolis","level":4,"short":0,"flag_type":"m","flag_code":"","section":0,"period":0},{"id":"sagalassus_rom_prov","text":"Sagalassus","level":4,"short":0,"flag_type":"m","flag_code":"","section":0,"period":0},{"id":"savatra_rom_prov","text":"Savatra","level":4,"short":0,"flag_type":"m","flag_code":"","section":0,"period":0},{"id":"tavium_rom_prov","text":"Tavium","level":4,"short":0,"flag_type":"m","flag_code":"","section":0,"period":0},{"id":"galatia_cappadocia_province","text":"Galatia-Cappadocia","level":3,"short":0,"flag_type":"s","flag_code":"roman-provinces","section":1,"period":0},{"id":"antioch_galatia_cap_rom_prov","text":"Antioch of Pisidia","level":4,"short":1,"flag_type":"m","flag_code":"","section":0,"period":0},{"id":"caesarea_gal_cap_rom_prov","text":"Caesarea","level":4,"short":1,"flag_type":"m","flag_code":"","section":0,"period":0},{"id":"cremna_gal_cap_rom_prov","text":"Cremna","level":4,"short":1,"flag_type":"m","flag_code":"","section":0,"period":0},{"id":"cybistra_rom_prov","text":"Cybistra","level":4,"short":0,"flag_type":"m","flag_code":"","section":0,"period":0},{"id":"koinon_galatia_cap_rom_prov","text":"Galatia, Koinon of","level":4,"short":1,"flag_type":"m","flag_code":"","section":0,"period":0},{"id":"hierapolis_rom_prov","text":"Hierapolis","level":4,"short":0,"flag_type":"m","flag_code":"","section":0,"period":0},{"id":"laodicea_catacecaumene_rom_prov","text":"Laodicea Catacecaumene","level":4,"short":0,"flag_type":"m","flag_code":"","section":0,"period":0},{"id":"sagalassus_gal_cap_rom_prov","text":"Sagalassus","level":4,"short":1,"flag_type":"m","flag_code":"","section":0,"period":0},{"id":"zela_rom_prov","text":"Zela","level":4,"short":0,"flag_type":"m","flag_code":"","section":0,"period":0},{"id":"galatia_pontus_province","text":"Galatia-Pontus","level":3,"short":0,"flag_type":"s","flag_code":"roman-provinces","section":1,"period":0},{"id":"antioch_galatia_pon_rom_prov","text":"Antioch of Pisidia","level":4,"short":1,"flag_type":"m","flag_code":"","section":0,"period":0},{"id":"gallia_belgica_province","text":"Gallia Belgica","level":3,"short":0,"flag_type":"s","flag_code":"roman-provinces","section":1,"period":0},{"id":"treveri_rom_prov","text":"Reims","level":4,"short":0,"flag_type":"m","flag_code":"","section":0,"period":0},{"id":"gallia_lugdunensis_province","text":"Gallia Lugdunensis","level":3,"short":0,"flag_type":"s","flag_code":"roman-provinces","section":1,"period":0},{"id":"lugdunum_rom_prov","text":"Lugdunum","level":4,"short":0,"flag_type":"m","flag_code":"","section":0,"period":0},{"id":"gallia_narbonensis_province","text":"Gallia Narbonensis","level":3,"short":0,"flag_type":"s","flag_code":"roman-provinces","section":1,"period":0},{"id":"antipolis_rom_prov","text":"Antipolis","level":4,"short":0,"flag_type":"m","flag_code":"","section":0,"period":0},{"id":"arausio_rom_prov","text":"Arausio","level":4,"short":0,"flag_type":"m","flag_code":"","section":0,"period":0},{"id":"cabellio_rom_prov","text":"Cabellio","level":4,"short":0,"flag_type":"m","flag_code":"","section":0,"period":0},{"id":"cavari_rom_prov","text":"Cavari","level":4,"short":0,"flag_type":"m","flag_code":"","section":0,"period":0},{"id":"forum_iulii_rom_prov","text":"Forum Iulii","level":4,"short":0,"flag_type":"m","flag_code":"","section":0,"period":0},{"id":"gaule_narbonnaise_rom_prov","text":"Gallia Narbonensis","level":4,"short":0,"flag_type":"m","flag_code":"","section":0,"period":0},{"id":"matavonium_rom_prov","text":"Matavonium","level":4,"short":0,"flag_type":"m","flag_code":"","section":0,"period":0},{"id":"narbo_rom_prov","text":"Narbo","level":4,"short":0,"flag_type":"m","flag_code":"","section":0,"period":0},{"id":"nemausus_rom_prov","text":"Nemausus","level":4,"short":0,"flag_type":"m","flag_code":"","section":0,"period":0},{"id":"vienna_rom_prov","text":"Vienna","level":4,"short":0,"flag_type":"m","flag_code":"","section":0,"period":0},{"id":"italia_roman_province","text":"Italy, Roman province of","level":3,"short":0,"flag_type":"s","flag_code":"roman-provinces","section":1,"period":0},{"id":"uncertain_northern_italy_rom","text":"Northern Italy, Uncertain City of","level":4,"short":0,"flag_type":"m","flag_code":"","section":0,"period":0},{"id":"paestum_rom_prov","text":"Paestum","level":4,"short":0,"flag_type":"m","flag_code":"","section":0,"period":0},{"id":"judaea_province","text":"Judaea","level":3,"short":0,"flag_type":"s","flag_code":"roman-provinces","section":1,"period":0},{"id":"ascalon_jud_rom_prov","text":"Ascalon","level":4,"short":1,"flag_type":"m","flag_code":"","section":0,"period":0},{"id":"caesarea_maritima_jud_rom_prov","text":"Caesarea Maritima","level":4,"short":0,"flag_type":"m","flag_code":"","section":0,"period":0},{"id":"caesarea_paneas_rom_prov","text":"Caesarea Paneas","level":4,"short":0,"flag_type":"m","flag_code":"","section":0,"period":0},{"id":"gaba_rom_prov","text":"Gaba","level":4,"short":0,"flag_type":"m","flag_code":"","section":0,"period":0},{"id":"gaza_jud_rom_prov","text":"Gaza","level":4,"short":0,"flag_type":"m","flag_code":"","section":0,"period":0},{"id":"jerusalem_rom_prov","text":"Jerusalem","level":4,"short":0,"flag_type":"m","flag_code":"","section":0,"period":0},{"id":"neapolis_jud_rom_prov","text":"Neapolis","level":4,"short":0,"flag_type":"m","flag_code":"","section":0,"period":0},{"id":"sepphoris_rom_prov","text":"Sepphoris","level":4,"short":0,"flag_type":"m","flag_code":"","section":0,"period":0},{"id":"tiberias_rom_prov","text":"Tiberias","level":4,"short":0,"flag_type":"m","flag_code":"","section":0,"period":0},{"id":"lusitania_hisp_province","text":"Lusitania","level":3,"short":0,"flag_type":"s","flag_code":"roman-provinces","section":1,"period":0},{"id":"baesuri_rom_prov","text":"Baesuri","level":4,"short":0,"flag_type":"m","flag_code":"","section":0,"period":0},{"id":"ebora_rom_prov","text":"Ebora","level":4,"short":0,"flag_type":"m","flag_code":"","section":0,"period":0},{"id":"emerita_rom_prov","text":"Emerita","level":4,"short":0,"flag_type":"m","flag_code":"","section":0,"period":0},{"id":"pax_iulia_rom_prov","text":"Pax Iulia","level":4,"short":0,"flag_type":"m","flag_code":"","section":0,"period":0},{"id":"salacia_rom_prov","text":"Salacia","level":4,"short":0,"flag_type":"m","flag_code":"","section":0,"period":0},{"id":"uncertain_lusitania_city","text":"Uncertain Lusitanian city","level":4,"short":0,"flag_type":"m","flag_code":"","section":0,"period":0},{"id":"lycia_pamphylia_province","text":"Lycia et Pamphylia","level":3,"short":0,"flag_type":"s","flag_code":"roman-provinces","section":1,"period":0},{"id":"acalissus_rom_prov","text":"Acalissus","level":4,"short":0,"flag_type":"m","flag_code":"","section":0,"period":0},{"id":"adada_rom_prov","text":"Adada","level":4,"short":0,"flag_type":"m","flag_code":"","section":0,"period":0},{"id":"amblada_rom_prov","text":"Amblada","level":4,"short":0,"flag_type":"m","flag_code":"","section":0,"period":0},{"id":"andeda_rom_prov","text":"Andeda","level":4,"short":0,"flag_type":"m","flag_code":"","section":0,"period":0},{"id":"antiphellus_rom_prov","text":"Antiphellus","level":4,"short":0,"flag_type":"m","flag_code":"","section":0,"period":0},{"id":"aperlae_rom_prov","text":"Aperlae","level":4,"short":0,"flag_type":"m","flag_code":"","section":0,"period":0},{"id":"ariassus_rom_prov","text":"Ariassus","level":4,"short":0,"flag_type":"m","flag_code":"","section":0,"period":0},{"id":"arneae_rom_prov","text":"Arneae","level":4,"short":0,"flag_type":"m","flag_code":"","section":0,"period":0},{"id":"arycanda_rom_prov","text":"Arycanda","level":4,"short":0,"flag_type":"m","flag_code":"","section":0,"period":0},{"id":"aspendus_roman_province","text":"Aspendus","level":4,"short":0,"flag_type":"m","flag_code":"","section":0,"period":0},{"id":"attalea_rom_prov","text":"Attalea","level":4,"short":0,"flag_type":"m","flag_code":"","section":0,"period":0},{"id":"balbura_rom_prov","text":"Balbura","level":4,"short":0,"flag_type":"m","flag_code":"","section":0,"period":0},{"id":"baris_rom_prov","text":"Baris","level":4,"short":0,"flag_type":"m","flag_code":"","section":0,"period":0},{"id":"bubon_rom_prov","text":"Bubon","level":4,"short":0,"flag_type":"m","flag_code":"","section":0,"period":0},{"id":"candyba_rom_prov","text":"Candyba","level":4,"short":0,"flag_type":"m","flag_code":"","section":0,"period":0},{"id":"choma_rom_prov","text":"Choma","level":4,"short":0,"flag_type":"m","flag_code":"","section":0,"period":0},{"id":"claudioseleucia_rom_prov","text":"Claudioseleucia","level":4,"short":0,"flag_type":"m","flag_code":"","section":0,"period":0},{"id":"codrula_rom_prov","text":"Codrula","level":4,"short":0,"flag_type":"m","flag_code":"","section":0,"period":0},{"id":"colbasa_rom_prov","text":"Colbasa","level":4,"short":0,"flag_type":"m","flag_code":"","section":0,"period":0},{"id":"comama_rom_prov","text":"Comama","level":4,"short":0,"flag_type":"m","flag_code":"","section":0,"period":0},{"id":"conana_rom_prov","text":"Conana","level":4,"short":0,"flag_type":"m","flag_code":"","section":0,"period":0},{"id":"cremna_lyc_pam_rom_prov","text":"Cremna","level":4,"short":1,"flag_type":"m","flag_code":"","section":0,"period":0},{"id":"cyaneae_rom_prov","text":"Cyaneae","level":4,"short":0,"flag_type":"m","flag_code":"","section":0,"period":0},{"id":"etenna_rom_prov","text":"Etenna","level":4,"short":0,"flag_type":"m","flag_code":"","section":0,"period":0},{"id":"gagae_rom_prov","text":"Gagae","level":4,"short":0,"flag_type":"m","flag_code":"","section":0,"period":0},{"id":"isinda_lyc_pam_rom_prov","text":"Isinda","level":4,"short":0,"flag_type":"m","flag_code":"","section":0,"period":0},{"id":"laertes_lyc_pamp_rom_prov","text":"Laertes","level":4,"short":0,"flag_type":"m","flag_code":"","section":0,"period":0},{"id":"limyra_rom_prov","text":"Limyra","level":4,"short":0,"flag_type":"m","flag_code":"","section":0,"period":0},{"id":"lycian_koinon_rom_prov","text":"Lycia, Koinon of","level":4,"short":0,"flag_type":"m","flag_code":"","section":0,"period":0},{"id":"lyrbe_rom_prov","text":"Lyrbe","level":4,"short":0,"flag_type":"m","flag_code":"","section":0,"period":0},{"id":"magydus_rom_prov","text":"Magydus","level":4,"short":0,"flag_type":"m","flag_code":"","section":0,"period":0},{"id":"myra_rom_prov","text":"Myra","level":4,"short":0,"flag_type":"m","flag_code":"","section":0,"period":0},{"id":"olbasa_rom_prov","text":"Olbasa","level":4,"short":0,"flag_type":"m","flag_code":"","section":0,"period":0},{"id":"olympus_rom_prov","text":"Olympus","level":4,"short":0,"flag_type":"m","flag_code":"","section":0,"period":0},{"id":"palaeopolis_rom_prov","text":"Palaeopolis","level":4,"short":0,"flag_type":"m","flag_code":"","section":0,"period":0},{"id":"panemoteichus_rom_prov","text":"Panemoteichus","level":4,"short":0,"flag_type":"m","flag_code":"","section":0,"period":0},{"id":"parlais_rom_prov","text":"Parlais","level":4,"short":0,"flag_type":"m","flag_code":"","section":0,"period":0},{"id":"patara_rom_prov","text":"Patara","level":4,"short":0,"flag_type":"m","flag_code":"","section":0,"period":0},{"id":"pednelissus_rom_prov","text":"Pednelissus","level":4,"short":0,"flag_type":"m","flag_code":"","section":0,"period":0},{"id":"perge_rom_prov","text":"Perge","level":4,"short":0,"flag_type":"m","flag_code":"","section":0,"period":0},{"id":"phaselis_rom_prov","text":"Phaselis","level":4,"short":0,"flag_type":"m","flag_code":"","section":0,"period":0},{"id":"phellus_rom_prov","text":"Phellus","level":4,"short":0,"flag_type":"m","flag_code":"","section":0,"period":0},{"id":"podalia_rom_prov","text":"Podalia","level":4,"short":0,"flag_type":"m","flag_code":"","section":0,"period":0},{"id":"pogla_rom_prov","text":"Pogla","level":4,"short":0,"flag_type":"m","flag_code":"","section":0,"period":0},{"id":"prostanna_rom_prov","text":"Prostanna","level":4,"short":0,"flag_type":"m","flag_code":"","section":0,"period":0},{"id":"rhodiapolis_rom_prov","text":"Rhodiapolis","level":4,"short":0,"flag_type":"m","flag_code":"","section":0,"period":0},{"id":"selge_rom_prov","text":"Selge","level":4,"short":0,"flag_type":"m","flag_code":"","section":0,"period":0},{"id":"sibidunda_rom_prov","text":"Sibidunda","level":4,"short":0,"flag_type":"m","flag_code":"","section":0,"period":0},{"id":"side_rom_prov","text":"Side","level":4,"short":0,"flag_type":"m","flag_code":"","section":0,"period":0},{"id":"sillyum_rom_prov","text":"Sillyum","level":4,"short":0,"flag_type":"m","flag_code":"","section":0,"period":0},{"id":"termessus_minor_rom_prov","text":"Termessus by Oenoanda","level":4,"short":0,"flag_type":"m","flag_code":"","section":0,"period":0},{"id":"termessus_major_rom_prov","text":"Termessus Major","level":4,"short":0,"flag_type":"m","flag_code":"","section":0,"period":0},{"id":"timbriada_rom_prov","text":"Timbriada","level":4,"short":0,"flag_type":"m","flag_code":"","section":0,"period":0},{"id":"tityassus_rom_prov","text":"Tityassus","level":4,"short":0,"flag_type":"m","flag_code":"","section":0,"period":0},{"id":"tlos_rom_prov","text":"Tlos","level":4,"short":0,"flag_type":"m","flag_code":"","section":0,"period":0},{"id":"trebenna_rom_prov","text":"Trebenna","level":4,"short":0,"flag_type":"m","flag_code":"","section":0,"period":0},{"id":"verbe_rom_prov","text":"Verbe","level":4,"short":0,"flag_type":"m","flag_code":"","section":0,"period":0},{"id":"macedonia_province","text":"Macedonia, Roman province of","level":3,"short":0,"flag_type":"s","flag_code":"roman-provinces","section":1,"period":0},{"id":"amphipolis_rom","text":"Amphipolis, City of","level":4,"short":0,"flag_type":"m","flag_code":"","section":0,"period":0},{"id":"beroea_macedon_rom_prov","text":"Beroea","level":4,"short":0,"flag_type":"m","flag_code":"","section":0,"period":0},{"id":"cassandrea_rom_prov","text":"Cassandrea","level":4,"short":0,"flag_type":"m","flag_code":"","section":0,"period":0},{"id":"dium_macedon_rom_prov","text":"Dium","level":4,"short":0,"flag_type":"m","flag_code":"","section":0,"period":0},{"id":"edessa_macedon_rom_prov","text":"Edessa","level":4,"short":0,"flag_type":"m","flag_code":"","section":0,"period":0},{"id":"heraclea_sintica_rom_prov","text":"Heraclea Sintica","level":4,"short":0,"flag_type":"m","flag_code":"","section":0,"period":0},{"id":"koinon_macedonia","text":"Macedonia, Koinon of","level":4,"short":0,"flag_type":"m","flag_code":"","section":0,"period":0},{"id":"pella_macedon_rom_prov","text":"Pella","level":4,"short":0,"flag_type":"m","flag_code":"","section":0,"period":0},{"id":"philippi_macedonia_rom_prov","text":"Philippi","level":4,"short":0,"flag_type":"m","flag_code":"","section":0,"period":0},{"id":"stobi_rom_prov","text":"Stobi","level":4,"short":0,"flag_type":"m","flag_code":"","section":0,"period":0},{"id":"thessalonica_macedonia_rom_prov","text":"Thessalonica","level":4,"short":0,"flag_type":"m","flag_code":"","section":0,"period":0},{"id":"mauretania_province","text":"Mauretania","level":3,"short":0,"flag_type":"s","flag_code":"roman-provinces","section":1,"period":0},{"id":"babba_rom_prov","text":"Babba","level":4,"short":0,"flag_type":"m","flag_code":"","section":0,"period":0},{"id":"cartenna_rom_prov","text":"Cartenna","level":4,"short":0,"flag_type":"m","flag_code":"","section":0,"period":0},{"id":"iol_rom_prov","text":"Iol","level":4,"short":0,"flag_type":"m","flag_code":"","section":0,"period":0},{"id":"tingi_rom_prov","text":"Tingi","level":4,"short":0,"flag_type":"m","flag_code":"","section":0,"period":0},{"id":"zilil_rom_prov","text":"Zilil","level":4,"short":0,"flag_type":"m","flag_code":"","section":0,"period":0},{"id":"mesopotamia_province","text":"Mesopotamia","level":3,"short":0,"flag_type":"s","flag_code":"roman-provinces","section":1,"period":0},{"id":"carrhae_rom_prov","text":"Carrhae","level":4,"short":0,"flag_type":"m","flag_code":"","section":0,"period":0},{"id":"edessa_mesopotamia_rom_prov","text":"Edessa (Mesopotamia)","level":4,"short":0,"flag_type":"m","flag_code":"","section":0,"period":0},{"id":"nisibis_rom_prov","text":"Nisibis","level":4,"short":0,"flag_type":"m","flag_code":"","section":0,"period":0},{"id":"rhesaena_rom_prov","text":"Rhesaena","level":4,"short":0,"flag_type":"m","flag_code":"","section":0,"period":0},{"id":"singara_rom_prov","text":"Singara","level":4,"short":0,"flag_type":"m","flag_code":"","section":0,"period":0},{"id":"moesia_province","text":"Moesia","level":3,"short":0,"flag_type":"s","flag_code":"roman-provinces","section":1,"period":0},{"id":"callatis_rom_prov","text":"Callatis","level":4,"short":0,"flag_type":"m","flag_code":"","section":0,"period":0},{"id":"dionysopolis_rom_prov","text":"Dionysopolis","level":4,"short":0,"flag_type":"m","flag_code":"","section":0,"period":0},{"id":"odessos_rom_prov","text":"Odessos","level":4,"short":0,"flag_type":"m","flag_code":"","section":0,"period":0},{"id":"tomis_rom_prov","text":"Tomis","level":4,"short":0,"flag_type":"m","flag_code":"","section":0,"period":0},{"id":"moesia_inferior_province","text":"Moesia Inferior","level":3,"short":0,"flag_type":"s","flag_code":"roman-provinces","section":1,"period":0},{"id":"callatis_moesia_inferior_rom_prov","text":"Callatis","level":4,"short":1,"flag_type":"m","flag_code":"","section":0,"period":0},{"id":"dionysopolis_moesia_inferior_rom_prov","text":"Dionysopolis","level":4,"short":1,"flag_type":"m","flag_code":"","section":0,"period":0},{"id":"histria_rom_prov","text":"Histria","level":4,"short":0,"flag_type":"m","flag_code":"","section":0,"period":0},{"id":"marcianopolis_rom_prov","text":"Marcianopolis","level":4,"short":0,"flag_type":"m","flag_code":"","section":0,"period":0},{"id":"nicopolis_rom_prov","text":"Nicopolis ad Istrum","level":4,"short":0,"flag_type":"m","flag_code":"","section":0,"period":0},{"id":"odessos_moesia_inferior_rom_prov","text":"Odessos","level":4,"short":1,"flag_type":"m","flag_code":"","section":0,"period":0},{"id":"tomis_moesia_inferior_rom_prov","text":"Tomis","level":4,"short":1,"flag_type":"m","flag_code":"","section":0,"period":0},{"id":"moesia_superior_province","text":"Moesia Superior","level":3,"short":0,"flag_type":"s","flag_code":"roman-provinces","section":1,"period":0},{"id":"callatis_moesia_superior_rom_prov","text":"Callatis","level":4,"short":1,"flag_type":"m","flag_code":"","section":0,"period":0},{"id":"viminacium_rom_prov","text":"Viminacium","level":4,"short":0,"flag_type":"m","flag_code":"","section":0,"period":0},{"id":"northern_black_sea_province","text":"Northern Black Sea","level":3,"short":0,"flag_type":"s","flag_code":"roman-provinces","section":1,"period":0},{"id":"chersonesus_rom_prov","text":"Chersonesus (Bosporus)","level":4,"short":0,"flag_type":"m","flag_code":"","section":0,"period":0},{"id":"olbia_rom_prov","text":"Olbia","level":4,"short":0,"flag_type":"m","flag_code":"","section":0,"period":0},{"id":"tyra_rom_prov","text":"Tyra","level":4,"short":0,"flag_type":"m","flag_code":"","section":0,"period":0},{"id":"sicilia_province","text":"Sicilia","level":3,"short":0,"flag_type":"s","flag_code":"roman-provinces","section":1,"period":0},{"id":"agrigentum_rom_prov","text":"Agrigentum","level":4,"short":0,"flag_type":"m","flag_code":"","section":0,"period":0},{"id":"assorus_rom_prov","text":"Assorus","level":4,"short":0,"flag_type":"m","flag_code":"","section":0,"period":0},{"id":"catane_rom_prov","text":"Catane, City of","level":4,"short":0,"flag_type":"m","flag_code":"","section":0,"period":0},{"id":"centuripae_rom_prov","text":"Centuripae","level":4,"short":0,"flag_type":"m","flag_code":"","section":0,"period":0},{"id":"cephaloedium_rom_prov","text":"Cephaloedium","level":4,"short":0,"flag_type":"m","flag_code":"","section":0,"period":0},{"id":"cossura_rom_prov","text":"Cossura","level":4,"short":0,"flag_type":"m","flag_code":"","section":0,"period":0},{"id":"entella_rom_prov","text":"Entella","level":4,"short":0,"flag_type":"m","flag_code":"","section":0,"period":0},{"id":"gaulos_island","text":"Gaulos, Island of","level":4,"short":0,"flag_type":"m","flag_code":"","section":0,"period":0},{"id":"halaesa_rom_prov","text":"Halaesa","level":4,"short":0,"flag_type":"m","flag_code":"","section":0,"period":0},{"id":"henna_rom_prov","text":"Henna","level":4,"short":0,"flag_type":"m","flag_code":"","section":0,"period":0},{"id":"iaiton_rom_prov","text":"Iaiton","level":4,"short":0,"flag_type":"m","flag_code":"","section":0,"period":0},{"id":"lilybaeum_rom_prov","text":"Lilybaeum","level":4,"short":0,"flag_type":"m","flag_code":"","section":0,"period":0},{"id":"lipara_rom_prov","text":"Lipara","level":4,"short":0,"flag_type":"m","flag_code":"","section":0,"period":0},{"id":"melita_rom_prov","text":"Melita","level":4,"short":0,"flag_type":"m","flag_code":"","section":0,"period":0},{"id":"panormus_rom_prov","text":"Panormus","level":4,"short":0,"flag_type":"m","flag_code":"","section":0,"period":0},{"id":"segesta_rom_prov","text":"Segesta","level":4,"short":0,"flag_type":"m","flag_code":"","section":0,"period":0},{"id":"tyndaris_rom_prov","text":"Tyndaris","level":4,"short":0,"flag_type":"m","flag_code":"","section":0,"period":0},{"id":"uncertain_roman_sicily_city","text":"Uncertain Sicilian city","level":4,"short":0,"flag_type":"m","flag_code":"","section":0,"period":0},{"id":"syria_province","text":"Syria","level":3,"short":0,"flag_type":"s","flag_code":"roman-provinces","section":1,"period":0},{"id":"antioch_ad_euphratem_rom_prov","text":"Antioch ad Euphratem","level":4,"short":0,"flag_type":"m","flag_code":"","section":0,"period":0},{"id":"antioch_hippum_rom_prov","text":"Antioch ad Hippum","level":4,"short":0,"flag_type":"m","flag_code":"","section":0,"period":0},{"id":"antioch_or_rom_prov","text":"Antioch on the Orontes","level":4,"short":0,"flag_type":"m","flag_code":"","section":0,"period":0},{"id":"apamea_ad_orontes_rom_prov","text":"Apamea ad Orontes","level":4,"short":0,"flag_type":"m","flag_code":"","section":0,"period":0},{"id":"ascalon_syr_rom_prov","text":"Ascalon","level":4,"short":0,"flag_type":"m","flag_code":"","section":0,"period":0},{"id":"beroea_rom_prov","text":"Beroea","level":4,"short":0,"flag_type":"m","flag_code":"","section":0,"period":0},{"id":"berytus_rom_prov","text":"Berytus","level":4,"short":0,"flag_type":"m","flag_code":"","section":0,"period":0},{"id":"byblus_rom_prov","text":"Byblus","level":4,"short":0,"flag_type":"m","flag_code":"","section":0,"period":0},{"id":"caesarea_maritima_syr_rom_prov","text":"Caesarea Maritima","level":4,"short":0,"flag_type":"m","flag_code":"","section":0,"period":0},{"id":"chalcis_bellum_rom_prov","text":"Chalcis ad Belum","level":4,"short":0,"flag_type":"m","flag_code":"","section":0,"period":0},{"id":"claudia_leucas_rom_prov","text":"Claudia Leucas","level":4,"short":0,"flag_type":"m","flag_code":"","section":0,"period":0},{"id":"cyrrhus_rom_prov","text":"Cyrrhus","level":4,"short":0,"flag_type":"m","flag_code":"","section":0,"period":0},{"id":"damascus_rom_prov","text":"Damascus","level":4,"short":0,"flag_type":"m","flag_code":"","section":0,"period":0},{"id":"demetrias_phoenice_rom_prov","text":"Demetrias","level":4,"short":0,"flag_type":"m","flag_code":"","section":0,"period":0},{"id":"doliche_rom_prov","text":"Doliche","level":4,"short":0,"flag_type":"m","flag_code":"","section":0,"period":0},{"id":"dora_rom_prov","text":"Dora","level":4,"short":0,"flag_type":"m","flag_code":"","section":0,"period":0},{"id":"emesa_rom_prov","text":"Emesa","level":4,"short":0,"flag_type":"m","flag_code":"","section":0,"period":0},{"id":"gabala_rom_prov","text":"Gabala","level":4,"short":0,"flag_type":"m","flag_code":"","section":0,"period":0},{"id":"gadara_syria_rom_prov","text":"Gadara","level":4,"short":0,"flag_type":"m","flag_code":"","section":0,"period":0},{"id":"gerasa_syria_rom_prov","text":"Gerasa","level":4,"short":0,"flag_type":"m","flag_code":"","section":0,"period":0},{"id":"germanicia_caesarea_rom_prov","text":"Germanicia Caesarea","level":4,"short":0,"flag_type":"m","flag_code":"","section":0,"period":0},{"id":"hierapolis_bamb_rom_prov","text":"Hierapolis Bambyce","level":4,"short":0,"flag_type":"m","flag_code":"","section":0,"period":0},{"id":"laodicea_mare_rom_prov","text":"Laodicea ad Mare","level":4,"short":0,"flag_type":"m","flag_code":"","section":0,"period":0},{"id":"marathus_phoenice_rom_prov","text":"Marathus","level":4,"short":0,"flag_type":"m","flag_code":"","section":0,"period":0},{"id":"nicopolis_seleucidis_rom_prov","text":"Nicopolis Seleucidis","level":4,"short":0,"flag_type":"m","flag_code":"","section":0,"period":0},{"id":"nysa_scythopolis_syr_rom_prov","text":"Nysa-Scythopolis","level":4,"short":0,"flag_type":"m","flag_code":"","section":0,"period":0},{"id":"pella_syria_rom_prov","text":"Pella","level":4,"short":0,"flag_type":"m","flag_code":"","section":0,"period":0},{"id":"philadelphia_syria_rom_prov","text":"Philadelphia","level":4,"short":0,"flag_type":"m","flag_code":"","section":0,"period":0},{"id":"samosata_rom_prov","text":"Samosata","level":4,"short":0,"flag_type":"m","flag_code":"","section":0,"period":0},{"id":"seleucia_pieria_rom_prov","text":"Seleucia Pieria","level":4,"short":0,"flag_type":"m","flag_code":"","section":0,"period":0},{"id":"sidon_rom_prov","text":"Sidon","level":4,"short":0,"flag_type":"m","flag_code":"","section":0,"period":0},{"id":"sistripia_rom_prov","text":"Sistripia","level":4,"short":0,"flag_type":"m","flag_code":"","section":0,"period":0},{"id":"tyre_rom_prov","text":"Tyre","level":4,"short":0,"flag_type":"m","flag_code":"","section":0,"period":0},{"id":"uncertain_syrian_city","text":"Uncertain Syrian city","level":4,"short":0,"flag_type":"m","flag_code":"","section":0,"period":0},{"id":"zeugma_rom_prov","text":"Zeugma","level":4,"short":0,"flag_type":"m","flag_code":"","section":0,"period":0},{"id":"syria_coele_province","text":"Syria Coele","level":3,"short":0,"flag_type":"s","flag_code":"roman-provinces","section":1,"period":0},{"id":"antioch_or_coele_rom_prov","text":"Antioch on the Orontes","level":4,"short":0,"flag_type":"m","flag_code":"","section":0,"period":0},{"id":"cyrrhus_coele_rom_prov","text":"Cyrrhus","level":4,"short":0,"flag_type":"m","flag_code":"","section":0,"period":0},{"id":"laodicea_ad_libanum_rom_prov","text":"Laodicea ad Libanum","level":4,"short":0,"flag_type":"m","flag_code":"","section":0,"period":0},{"id":"laodicea_mare_coele_rom_prov","text":"Laodicea ad Mare","level":4,"short":0,"flag_type":"m","flag_code":"","section":0,"period":0},{"id":"paltus_rom_prov","text":"Paltus","level":4,"short":0,"flag_type":"m","flag_code":"","section":0,"period":0},{"id":"raphanea_rom_prov","text":"Raphanea","level":4,"short":0,"flag_type":"m","flag_code":"","section":0,"period":0},{"id":"syria_palaestina_province","text":"Syria Palaestina","level":3,"short":0,"flag_type":"s","flag_code":"roman-provinces","section":1,"period":0},{"id":"aelia_capitolina_rom_prov","text":"Aelia Capitolina","level":4,"short":0,"flag_type":"m","flag_code":"","section":0,"period":0},{"id":"ascalon_rom_prov","text":"Ascalon","level":4,"short":1,"flag_type":"m","flag_code":"","section":0,"period":0},{"id":"caesarea_maritima_rom_prov","text":"Caesarea Maritima","level":4,"short":0,"flag_type":"m","flag_code":"","section":0,"period":0},{"id":"diospolis_rom_prov","text":"Diospolis","level":4,"short":0,"flag_type":"m","flag_code":"","section":0,"period":0},{"id":"eleutheropolis_rom_prov","text":"Eleutheropolis","level":4,"short":0,"flag_type":"m","flag_code":"","section":0,"period":0},{"id":"gaza_rom_prov","text":"Gaza","level":4,"short":0,"flag_type":"m","flag_code":"","section":0,"period":0},{"id":"neapolis_rom_prov","text":"Neapolis","level":4,"short":0,"flag_type":"m","flag_code":"","section":0,"period":0},{"id":"raphia_rom_prov","text":"Raphia","level":4,"short":0,"flag_type":"m","flag_code":"","section":0,"period":0},{"id":"sebaste_rom_prov","text":"Sebaste","level":4,"short":0,"flag_type":"m","flag_code":"","section":0,"period":0},{"id":"syria_phoenice_province","text":"Syria Phoenice","level":3,"short":0,"flag_type":"s","flag_code":"roman-provinces","section":1,"period":0},{"id":"aradus_phoenice_rom_prov","text":"Aradus","level":4,"short":0,"flag_type":"m","flag_code":"","section":0,"period":0},{"id":"botrys_phoenice_rom_prov","text":"Botrys","level":4,"short":0,"flag_type":"m","flag_code":"","section":0,"period":0},{"id":"caesarea_ad_libanum_phoenice_rom_prov","text":"Caesarea ad Libanum","level":4,"short":0,"flag_type":"m","flag_code":"","section":0,"period":0},{"id":"emesa_phoenice_rom_prov","text":"Emesa","level":4,"short":1,"flag_type":"m","flag_code":"","section":0,"period":0},{"id":"heliopolis_rom_prov","text":"Heliopolis","level":4,"short":0,"flag_type":"m","flag_code":"","section":0,"period":0},{"id":"orthosia_phoenice_rom_prov","text":"Orthosia","level":4,"short":0,"flag_type":"m","flag_code":"","section":0,"period":0},{"id":"ptolemais_phoenice_rom_prov","text":"Ptolemais","level":4,"short":0,"flag_type":"m","flag_code":"","section":0,"period":0},{"id":"tripolis_phoenice_rom_prov","text":"Tripolis","level":4,"short":0,"flag_type":"m","flag_code":"","section":0,"period":0},{"id":"tarraconensis_hisp_province","text":"Tarraconensis","level":3,"short":0,"flag_type":"s","flag_code":"roman-provinces","section":1,"period":0},{"id":"acci_rom_prov","text":"Acci","level":4,"short":0,"flag_type":"m","flag_code":"","section":0,"period":0},{"id":"bilbilis_rom_prov","text":"Bilbilis","level":4,"short":0,"flag_type":"m","flag_code":"","section":0,"period":0},{"id":"caesaraugusta_rom_prov","text":"Caesaraugusta","level":4,"short":0,"flag_type":"m","flag_code":"","section":0,"period":0},{"id":"calagurris_rom_prov","text":"Calagurris","level":4,"short":0,"flag_type":"m","flag_code":"","section":0,"period":0},{"id":"carthago_nova_rom_prov","text":"Carthago Nova","level":4,"short":0,"flag_type":"m","flag_code":"","section":0,"period":0},{"id":"cascantum_rom_prov","text":"Cascantum","level":4,"short":0,"flag_type":"m","flag_code":"","section":0,"period":0},{"id":"castulonian_mines_rom_prov","text":"Castulonian Mines","level":4,"short":0,"flag_type":"m","flag_code":"","section":0,"period":0},{"id":"celsa_rom_prov","text":"Celsa","level":4,"short":0,"flag_type":"m","flag_code":"","section":0,"period":0},{"id":"clunia_rom_prov","text":"Clunia","level":4,"short":0,"flag_type":"m","flag_code":"","section":0,"period":0},{"id":"consabrum_rom_prov","text":"Consabrum","level":4,"short":0,"flag_type":"m","flag_code":"","section":0,"period":0},{"id":"ebusus_rom_prov","text":"Ebusus","level":4,"short":0,"flag_type":"m","flag_code":"","section":0,"period":0},{"id":"emporia","text":"Emporia, City of","level":4,"short":0,"flag_type":"m","flag_code":"","section":0,"period":0},{"id":"ercavica_rom_prov","text":"Ercavica","level":4,"short":0,"flag_type":"m","flag_code":"","section":0,"period":0},{"id":"graccurris_rom_prov","text":"Graccurris","level":4,"short":0,"flag_type":"m","flag_code":"","section":0,"period":0},{"id":"ilercavonia-dertosa","text":"Ilercavonia-Dertosa","level":4,"short":0,"flag_type":"m","flag_code":"","section":0,"period":0},{"id":"ilerda_rom_prov","text":"Ilerda","level":4,"short":0,"flag_type":"m","flag_code":"","section":0,"period":0},{"id":"ilici","text":"Ilici, City of","level":4,"short":0,"flag_type":"m","flag_code":"","section":0,"period":0},{"id":"osca_rom_prov","text":"Osca","level":4,"short":0,"flag_type":"m","flag_code":"","section":0,"period":0},{"id":"osicerda_rom_prov","text":"Osicerda","level":4,"short":0,"flag_type":"m","flag_code":"","section":0,"period":0},{"id":"saguntum_rom_prov","text":"Saguntum","level":4,"short":0,"flag_type":"m","flag_code":"","section":0,"period":0},{"id":"segobriga_rom_prov","text":"Seg\u00f3briga","level":4,"short":0,"flag_type":"m","flag_code":"","section":0,"period":0},{"id":"segovia_rom_prov","text":"Segovia","level":4,"short":0,"flag_type":"m","flag_code":"","section":0,"period":0},{"id":"tarraco_rom_prov","text":"Tarraco","level":4,"short":0,"flag_type":"m","flag_code":"","section":0,"period":0},{"id":"turiaso_rom_prov","text":"Turiaso","level":4,"short":0,"flag_type":"m","flag_code":"","section":0,"period":0},{"id":"thracia_province","text":"Thracia","level":3,"short":0,"flag_type":"s","flag_code":"roman-provinces","section":1,"period":0},{"id":"abdera_thracia_rom_prov","text":"Abdera (Thracia)","level":4,"short":0,"flag_type":"m","flag_code":"","section":0,"period":0},{"id":"aenus_rom_prov","text":"Aenus","level":4,"short":0,"flag_type":"m","flag_code":"","section":0,"period":0},{"id":"anchialus_rom_prov","text":"Anchialus","level":4,"short":0,"flag_type":"m","flag_code":"","section":0,"period":0},{"id":"apollonia_pontica_rom_prov","text":"Apollonia Pontica","level":4,"short":0,"flag_type":"m","flag_code":"","section":0,"period":0},{"id":"augusta_traiana_rom_prov","text":"Augusta Traiana","level":4,"short":0,"flag_type":"m","flag_code":"","section":0,"period":0},{"id":"bizya_rom_prov","text":"Bizya","level":4,"short":0,"flag_type":"m","flag_code":"","section":0,"period":0},{"id":"byzantium_rom_prov","text":"Byzantium","level":4,"short":0,"flag_type":"m","flag_code":"","section":0,"period":0},{"id":"coela_rom_prov","text":"Coela","level":4,"short":0,"flag_type":"m","flag_code":"","section":0,"period":0},{"id":"deultum_rom_prov","text":"Deultum","level":4,"short":0,"flag_type":"m","flag_code":"","section":0,"period":0},{"id":"elaeus_rom_prov","text":"Elaeus","level":4,"short":0,"flag_type":"m","flag_code":"","section":0,"period":0},{"id":"hadrianopolis_thracia_rom_prov","text":"Hadrianopolis","level":4,"short":0,"flag_type":"m","flag_code":"","section":0,"period":0},{"id":"hephaestia_rom_prov","text":"Hephaestia","level":4,"short":0,"flag_type":"m","flag_code":"","section":0,"period":0},{"id":"imbrus_rom_prov","text":"Imbrus","level":4,"short":0,"flag_type":"m","flag_code":"","section":0,"period":0},{"id":"lemnus_rom_prov","text":"Lemnus","level":4,"short":0,"flag_type":"m","flag_code":"","section":0,"period":0},{"id":"maronea_rom_prov","text":"Maronea","level":4,"short":0,"flag_type":"m","flag_code":"","section":0,"period":0},{"id":"mesambria_rom_prov","text":"Mesambria","level":4,"short":0,"flag_type":"m","flag_code":"","section":0,"period":0},{"id":"nicopolis_thracia_rom_prov","text":"Nicopolis ad Nestum","level":4,"short":0,"flag_type":"m","flag_code":"","section":0,"period":0},{"id":"pautalia_rom_prov","text":"Pautalia","level":4,"short":0,"flag_type":"m","flag_code":"","section":0,"period":0},{"id":"perinthus_rom_prov","text":"Perinthus","level":4,"short":0,"flag_type":"m","flag_code":"","section":0,"period":0},{"id":"philippopolis_thracia_rom_prov","text":"Philippopolis","level":4,"short":0,"flag_type":"m","flag_code":"","section":0,"period":0},{"id":"plotinopolis_rom_prov","text":"Plotinopolis","level":4,"short":0,"flag_type":"m","flag_code":"","section":0,"period":0},{"id":"serdica_rom_prov","text":"Serdica","level":4,"short":0,"flag_type":"m","flag_code":"","section":0,"period":0},{"id":"sestus_rom_prov","text":"Sestus","level":4,"short":0,"flag_type":"m","flag_code":"","section":0,"period":0}],"pagination":{"more":true}}